{"cameraMode":{"drawMode":0,"name":"Shaded","section":"Shading Mode"},"sceneLighting":true,"audioPlay":false,"sceneViewState":{"showFog":true,"showMaterialUpdate":false,"showSkybox":true,"showFlares":true,"showImageEffects":true,"showParticleSystems":true},"in2DMode":false,"pivot":{"x":8.419120788574219,"y":-26.559669494628908,"z":15.836212158203125},"rotation":{"x":-0.25167137384414675,"y":-0.660809338092804,"z":0.2516763508319855,"w":-0.6607961654663086},"size":140.3521728515625,"orthographic":false}